myanimelistpy/__init__.py
myanimelistpy/myanimelist.py
myanimelistpy/enums/__init__.py
myanimelistpy/enums/airingStatusEnum.py
myanimelistpy/enums/dayWeekEnum.py
myanimelistpy/enums/fieldsEnum.py
myanimelistpy/enums/mediaTypeEnum.py
myanimelistpy/enums/nsfwEnum.py
myanimelistpy/enums/ratingEnum.py
myanimelistpy/enums/relationTypeEnum.py
myanimelistpy/enums/seasonEnum.py
myanimelistpy/enums/sourceEnum.py
myanimelistpy/models/__init__.py
myanimelistpy/models/alternativeTitles.py
myanimelistpy/models/anime.py
myanimelistpy/models/broadcast.py
myanimelistpy/models/genre.py
myanimelistpy/models/node.py
myanimelistpy/models/picture.py
myanimelistpy/models/recommendation.py
myanimelistpy/models/relatedNode.py
myanimelistpy/models/season.py
myanimelistpy/models/statistics.py
myanimelistpy/models/statisticsStatus.py
myanimelistpy/models/studio.py
myanimelistpy/services/__init__.py
myanimelistpy/services/validateFields.py
myanimelistpy-0.1.4.dist-info/License
myanimelistpy-0.1.4.dist-info/METADATA
myanimelistpy-0.1.4.dist-info/WHEEL
myanimelistpy-0.1.4.dist-info/top_level.txt
myanimelistpy-0.1.4.dist-info/RECORD
