Metadata-Version: 2.1
Name: myanimelistpy
Version: 0.1.4
Summary: A library to use the MyAnimeList API more easily.
Home-page: https://github.com/AllanCapistrano/myanimelistpy
Author: AllanCapistrano
Author-email: asantos@ecomp.uefs.br
License: GNU General Public License v3 (GPLv3)
Project-URL: Documentation, https://myanimelistpy.readthedocs.io/en/latest/
Project-URL: Issue tracker, https://github.com/AllanCapistrano/myanimelistpy/issues
Classifier: Development Status :: 4 - Beta
Classifier: Intended Audience :: Developers
Classifier: Operating System :: OS Independent
Classifier: Programming Language :: Python :: 3.10
Classifier: Topic :: Software Development :: Libraries
Classifier: Topic :: Software Development :: Libraries :: Python Modules
Classifier: License :: OSI Approved :: GNU General Public License v3 (GPLv3)
Requires-Python: >=3.10.0
License-File: License
Requires-Dist: requests (==2.28.1)
